nbjuniper/__init__.py
nbjuniper/cli.py
nbjuniper-0.3.3.dist-info/entry_points.txt
nbjuniper-0.3.3.dist-info/LICENSE.txt
nbjuniper-0.3.3.dist-info/WHEEL
nbjuniper-0.3.3.dist-info/METADATA
nbjuniper-0.3.3.dist-info/RECORD
