Metadata-Version: 2.1
Name: nbjuniper
Version: 0.3.3
Summary: Convert Jupyter Notebooks into runnable HTML files with Juniper (https://github.com/ines/juniper).
Home-page: https://github.com/ashtonmv/nbjuniper
License: MIT
Author: Michael Ashton
Author-email: ashtonmv@gmail.com
Requires-Python: >=3.7,<4.0
Classifier: License :: OSI Approved :: MIT License
Classifier: Programming Language :: Python :: 3
Classifier: Programming Language :: Python :: 3.7
Classifier: Programming Language :: Python :: 3.8
Requires-Dist: markdown (>=3.2.2,<4.0.0)
Requires-Dist: pyyaml (>=5.3.1,<6.0.0)
Project-URL: Repository, https://github.com/ashtonmv/nbjuniper
